ConsoleM/__init__.py
ConsoleM/Core/__init__.py
ConsoleM/Core/linux_driver.py
ConsoleM/Core/terminal.py
ConsoleM/Core/windows_driver.py
ConsoleM/Core/const/__init__.py
ConsoleM/Core/const/keys.py
ConsoleM/Style/__init__.py
ConsoleM/Style/render.py
ConsoleM/Style/text.py
ConsoleM/Style/const/__init__.py
ConsoleM/Style/const/ascii.py
ConsoleM/Style/const/color.py
ConsoleM/Style/const/emoji.py
ConsoleM/Style/const/style.py
consolem-0.1.11.dist-info/licenses/LICENSE
consolem-0.1.11.dist-info/METADATA
consolem-0.1.11.dist-info/WHEEL
consolem-0.1.11.dist-info/top_level.txt
consolem-0.1.11.dist-info/RECORD
