Metadata-Version: 2.4
Name: ConsoleM
Version: 0.1.11
Summary: A powerful Python library for terminal manipulation and text styling
Home-page: https://github.com/Remi-Avec-Un-I/ConsoleM
Author: Remi
License: MIT
Project-URL: Homepage, https://github.com/yourusername/ConsoleM
Project-URL: Bug Tracker, https://github.com/yourusername/ConsoleM/issues
Keywords: terminal,console,text styling,cursor control,keyboard input
Classifier: Development Status :: 3 - Alpha
Classifier: Intended Audience :: Developers
Classifier: Topic :: Software Development :: Libraries :: Python Modules
Classifier: License :: OSI Approved :: MIT License
Classifier: Programming Language :: Python :: 3
Classifier: Programming Language :: Python :: 3.10
Classifier: Programming Language :: Python :: 3.11
Classifier: Programming Language :: Python :: 3.12
Classifier: Operating System :: OS Independent
Requires-Python: >=3.10
License-File: LICENSE
Dynamic: home-page
Dynamic: license-file
Dynamic: requires-python
